[
  {
    "id": "it-services",
    "title": "IT Services",
    "description": "Request IT support and services",
    "icon": "tools"
  },
  {
    "id": "human-resources",
    "title": "Human Resources",
    "description": "Access benefits, leave, and HR services",
    "icon": "clipboard"
  },
  {
    "id": "operations",
    "title": "Operations",
    "description": "Events, recruitment, and firm initiatives",
    "icon": "gear"
  },
  {
    "id": "knowledge",
    "title": "Knowledge",
    "description": "Find answers and documentation",
    "icon": "lightbulb"
  },
  {
    "id": "expense-report",
    "title": "Expense Report",
    "description": "Submit an expense for reimbursement",
    "icon": "receipt"
  },
  {
    "id": "firm-initiatives",
    "title": "Firm Initiatives",
    "description": "Select your Firm Initiatives for the year",
    "icon": "star"
  }
]
